notedx_sdk/__init__.py
notedx_sdk/account/__init__.py
notedx_sdk/account/account_manager.py
notedx_sdk/api_keys/__init__.py
notedx_sdk/api_keys/key_manager.py
notedx_sdk/client.py
notedx_sdk/core/__init__.py
notedx_sdk/core/note_manager.py
notedx_sdk/exceptions.py
notedx_sdk/helpers.py
notedx_sdk/usage/__init__.py
notedx_sdk/usage/usage_manager.py
notedx_sdk/webhooks/__init__.py
notedx_sdk/webhooks/webhook_manager.py
notedx_sdk-0.1.11.dist-info/LICENSE
notedx_sdk-0.1.11.dist-info/METADATA
notedx_sdk-0.1.11.dist-info/WHEEL
notedx_sdk-0.1.11.dist-info/entry_points.txt
notedx_sdk-0.1.11.dist-info/RECORD
