Metadata-Version: 2.3
Name: notedx-sdk
Version: 0.1.11
Summary: Official Python SDK for the NoteDx API - a powerful medical note generation service, fully compliant to healthcare regulations in the US and Canada.
License: Proprietary
Keywords: medical,notes,transcription,healthcare,api,AI,scribe,AI-scribe,pharmacy,nursing,radiology,procedures,medicalSpecialties,HIPAA,PIPEDA,Canada,USA,Quebec
Author: Julien Martel
Requires-Python: >=3.8.2,<4.0.0
Classifier: Development Status :: 4 - Beta
Classifier: Intended Audience :: Healthcare Industry
Classifier: License :: Other/Proprietary License
Classifier: Programming Language :: Python :: 3
Classifier: Programming Language :: Python :: 3.9
Classifier: Programming Language :: Python :: 3.10
Classifier: Programming Language :: Python :: 3.11
Classifier: Programming Language :: Python :: 3.12
Classifier: Programming Language :: Python :: 3.13
Classifier: Programming Language :: Python :: 3.8
Classifier: Topic :: Scientific/Engineering :: Medical Science Apps.
Classifier: Topic :: Software Development :: Libraries :: Python Modules
Requires-Dist: requests (>=2.31.0,<3.0.0)
Project-URL: Documentation, https://martelman.github.io/NoteDx-API-Client/
Project-URL: Homepage, https://www.notedxai.com/contact-8-1
Project-URL: Repository, https://github.com/martelman/NoteDx-API-Client
